Metadata-Version: 2.1
Name: blingfire
Version: 0.1.8
Summary: Python wrapper of lightning fast Finite State Machine based NLP library.
Home-page: https://github.com/microsoft/blingfire/
Author: Bling
Author-email: bling@microsoft.com
License: UNKNOWN
Platform: UNKNOWN
Classifier: Programming Language :: Python :: 3
Classifier: License :: OSI Approved :: MIT License
Classifier: Operating System :: OS Independent
